synodic_tools/__init__.py
synodic_tools/__main__ .py
synodic_tools/app.py
synodic_tools-0.1.0.dist-info/entry_points.txt
synodic_tools-0.1.0.dist-info/LICENSE.md
synodic_tools-0.1.0.dist-info/WHEEL
synodic_tools-0.1.0.dist-info/METADATA
synodic_tools-0.1.0.dist-info/RECORD
