Metadata-Version: 2.1
Name: synodic-tools
Version: 0.1.0
Summary:  A Python library to provide tooling support for the majority of Synodic software.
Home-page: https://github.com/Synodic-Software/Synodic-Tools
License: MIT
Author: Synodic Software
Requires-Python: >=3.8,<4.0
Classifier: License :: OSI Approved :: MIT License
Classifier: Programming Language :: Python :: 3
Classifier: Programming Language :: Python :: 3.8
Requires-Dist: click (>=7.0,<8.0)
Requires-Dist: gitpython (>=3.0.3,<4.0.0)
Requires-Dist: semantic_version (>=2.8.2,<3.0.0)
Requires-Dist: synodic-poetry (>=0.1,<0.2)
Project-URL: Repository, https://github.com/Synodic-Software/Synodic-Tools
